pytest_clarity/__init__.py
pytest_clarity/diff.py
pytest_clarity/hints.py
pytest_clarity/output.py
pytest_clarity/plugin.py
pytest_clarity/util.py
pytest_clarity-0.1.0a1.dist-info/LICENSE
pytest_clarity-0.1.0a1.dist-info/METADATA
pytest_clarity-0.1.0a1.dist-info/WHEEL
pytest_clarity-0.1.0a1.dist-info/entry_points.txt
pytest_clarity-0.1.0a1.dist-info/top_level.txt
pytest_clarity-0.1.0a1.dist-info/RECORD
