Metadata-Version: 2.1
Name: pytest-clarity
Version: 0.1.0a1
Summary: A plugin providing an alternative, colourful diff output for failing assertions.
Home-page: https://github.com/darrenburns/pytest-clarity
Author: Darren Burns
Author-email: darrenb900@gmail.com
Maintainer: Darren Burns
Maintainer-email: darrenb900@gmail.com
License: MIT
Platform: UNKNOWN
Classifier: Development Status :: 3 - Alpha
Classifier: Framework :: Pytest
Classifier: Intended Audience :: Developers
Classifier: Topic :: Software Development :: Testing
Classifier: Programming Language :: Python
Classifier: Programming Language :: Python :: 2
Classifier: Programming Language :: Python :: 2.7
Classifier: Programming Language :: Python :: 3
Classifier: Programming Language :: Python :: 3.4
Classifier: Programming Language :: Python :: 3.5
Classifier: Programming Language :: Python :: 3.6
Classifier: Programming Language :: Python :: Implementation :: CPython
Classifier: Operating System :: OS Independent
Classifier: License :: OSI Approved :: MIT License
Requires-Python: >=2.7, !=3.0.*, !=3.1.*, !=3.2.*, !=3.3.*
Requires-Dist: pytest (>=3.5.0)
Requires-Dist: termcolor (==1.1.0)
